getchanges/__init__.py
getchanges/__main__.py
getchanges/clog.py
getchanges/version.py
getchanges/hosts/__init__.py
getchanges/hosts/base.py
getchanges/hosts/github.py
getchanges/hosts/readthedocs.py
getchanges/indexes/__init__.py
getchanges/indexes/base.py
getchanges/indexes/pypi.py
getchanges-0.1.0.dist-info/LICENSE.txt
getchanges-0.1.0.dist-info/METADATA
getchanges-0.1.0.dist-info/WHEEL
getchanges-0.1.0.dist-info/entry_points.txt
getchanges-0.1.0.dist-info/top_level.txt
getchanges-0.1.0.dist-info/RECORD
