Metadata-Version: 2.1
Name: getchanges
Version: 0.1.0
Summary: getchanges is a utility for retrieving changelogs
Home-page: https://github.com/TheKevJames/experiments/blob/master/getchanges
Author: Kevin James
Author-email: KevinJames@thekev.in
License: MIT
Project-URL: Changelog, https://github.com/TheKevJames/experiments/blob/master/getchanges/CHANGELOG.md
Platform: Posix; MacOS X; Windows
Classifier: Development Status :: 3 - Alpha
Classifier: Intended Audience :: Developers
Classifier: Intended Audience :: End Users/Desktop
Classifier: License :: OSI Approved :: MIT License
Classifier: Natural Language :: English
Classifier: Operating System :: OS Independent
Classifier: Programming Language :: Python
Classifier: Programming Language :: Python :: 3 :: Only
Classifier: Programming Language :: Python :: 3.6
Classifier: Programming Language :: Python :: 3.7
Requires-Python: >= 3.5
Requires-Dist: aiohttp (==3.5.4)
Requires-Dist: docopt (==0.6.2)
Requires-Dist: yarl (==1.3.0)
